data_structures/__init__.py
data_structures/example.py
data_structure_practice-0.0.2.dist-info/LICENSE
data_structure_practice-0.0.2.dist-info/METADATA
data_structure_practice-0.0.2.dist-info/WHEEL
data_structure_practice-0.0.2.dist-info/entry_points.txt
data_structure_practice-0.0.2.dist-info/top_level.txt
data_structure_practice-0.0.2.dist-info/RECORD
