Metadata-Version: 2.1
Name: data-structure-practice
Version: 0.0.2
Summary: Practice data structures with Python
Home-page: https://github.com/pypa/sampleproject
Author: Jack Fragassi
Author-email: jack.fragassi@gmail.com
License: UNKNOWN
Project-URL: Bug Tracker, https://github.com/pypa/sampleproject/issues
Platform: UNKNOWN
Classifier: Development Status :: 3 - Alpha
Classifier: Programming Language :: Python :: 3
Classifier: License :: OSI Approved :: MIT License
Classifier: Operating System :: OS Independent
Requires-Python: >=3.7
License-File: LICENSE
